taxi_clockify/__init__.py
taxi_clockify/backend.py
taxi_clockify-1.5.0.dist-info/entry_points.txt
taxi_clockify-1.5.0.dist-info/LICENSE
taxi_clockify-1.5.0.dist-info/WHEEL
taxi_clockify-1.5.0.dist-info/METADATA
taxi_clockify-1.5.0.dist-info/RECORD
