Metadata-Version: 2.1
Name: taxi_clockify
Version: 1.5.0
Summary: Taxi backend for Clockify
Author-email: Sylvain Fankhauser <sephi@fhtagn.top>
Requires-Python: >=3.7
Requires-Dist: requests>=2.3.0
Requires-Dist: taxi~=6.0
Requires-Dist: arrow>=0.15.8
Project-URL: Source, https://github.com/sephii/taxi-clockify
